__init__.py
__main__.py
lib/__init__.py
lib/meteorfile.py
lib/venv_manage.py
meteorpy-0.0.3.dist-info/LICENSE
meteorpy-0.0.3.dist-info/METADATA
meteorpy-0.0.3.dist-info/WHEEL
meteorpy-0.0.3.dist-info/top_level.txt
meteorpy-0.0.3.dist-info/RECORD
