Metadata-Version: 2.1
Name: meteorpy
Version: 0.0.3
Summary: A tool to share python environment by building it from scratch on target machines.
Home-page: https://github.com/aerocyber/meteorpy/
Author: aerocyber
License: UNKNOWN
Project-URL: Bug Tracker, https://github.com/aerocyber/meteorpy/issues
Platform: UNKNOWN
Classifier: Programming Language :: Python :: 3
Classifier: License :: OSI Approved :: MIT License
Classifier: Operating System :: OS Independent
Requires-Python: >=3.6
License-File: LICENSE
